reprypt/__init__.py
reprypt/__main__.py
reprypt/py.typed
reprypt-2.2.6.dist-info/LICENSE
reprypt-2.2.6.dist-info/METADATA
reprypt-2.2.6.dist-info/WHEEL
reprypt-2.2.6.dist-info/entry_points.txt
reprypt-2.2.6.dist-info/top_level.txt
reprypt-2.2.6.dist-info/RECORD
