Metadata-Version: 2.1
Name: reprypt
Version: 2.2.6
Summary: Encryption Module
Home-page: https://github.com/tasuren/reprypt
Author: tasuren
Author-email: tasuren5@gmail.com
License: MIT
Project-URL: Documentation, https://tasuren.github.io/reprypt
Keywords: encrypt decrypt encryption
Platform: UNKNOWN
Classifier: Programming Language :: Python :: 3.8
Classifier: Programming Language :: Python :: 3.9
Classifier: Programming Language :: Python :: 3.10
Classifier: Typing :: Typed
License-File: LICENSE
